mcp_ai_jerry/__init__.py
mcp_ai_jerry/__main__.py
mcp_ai_jerry/debug.py
mcp_ai_jerry/i18n.py
mcp_ai_jerry/py.typed
mcp_ai_jerry/server.py
mcp_ai_jerry/auth/__init__.py
mcp_ai_jerry/auth/api_client.py
mcp_ai_jerry/auth/device_fingerprint.py
mcp_ai_jerry/auth/license_manager.py
mcp_ai_jerry/desktop_app/__init__.py
mcp_ai_jerry/desktop_app/desktop_app.py
mcp_ai_jerry/desktop_release/__init__.py
mcp_ai_jerry/desktop_release/mcp-ai-jerry-desktop-linux
mcp_ai_jerry/desktop_release/mcp-ai-jerry-desktop-macos-arm64
mcp_ai_jerry/desktop_release/mcp-ai-jerry-desktop-macos-intel
mcp_ai_jerry/desktop_release/mcp-ai-jerry-desktop.exe
mcp_ai_jerry/utils/__init__.py
mcp_ai_jerry/utils/error_handler.py
mcp_ai_jerry/utils/memory_monitor.py
mcp_ai_jerry/utils/resource_manager.py
mcp_ai_jerry/web/__init__.py
mcp_ai_jerry/web/main.py
mcp_ai_jerry/web/constants/__init__.py
mcp_ai_jerry/web/constants/message_codes.py
mcp_ai_jerry/web/locales/en/translation.json
mcp_ai_jerry/web/locales/zh-CN/translation.json
mcp_ai_jerry/web/locales/zh-TW/translation.json
mcp_ai_jerry/web/models/__init__.py
mcp_ai_jerry/web/models/feedback_result.py
mcp_ai_jerry/web/models/feedback_session.py
mcp_ai_jerry/web/routes/__init__.py
mcp_ai_jerry/web/routes/auth_routes.py
mcp_ai_jerry/web/routes/main_routes.py
mcp_ai_jerry/web/static/favicon.ico
mcp_ai_jerry/web/static/icon-192.png
mcp_ai_jerry/web/static/icon.svg
mcp_ai_jerry/web/static/index.html
mcp_ai_jerry/web/static/css/audio-management.css
mcp_ai_jerry/web/static/css/license-status.css
mcp_ai_jerry/web/static/css/notification-settings.css
mcp_ai_jerry/web/static/css/prompt-management.css
mcp_ai_jerry/web/static/css/session-management.css
mcp_ai_jerry/web/static/css/styles.css
mcp_ai_jerry/web/static/js/app.js
mcp_ai_jerry/web/static/js/i18n.js
mcp_ai_jerry/web/static/js/modules/connection-monitor.js
mcp_ai_jerry/web/static/js/modules/file-upload-manager.js
mcp_ai_jerry/web/static/js/modules/image-handler.js
mcp_ai_jerry-2.0.13.dist-info/METADATA
mcp_ai_jerry-2.0.13.dist-info/WHEEL
mcp_ai_jerry-2.0.13.dist-info/entry_points.txt
mcp_ai_jerry-2.0.13.dist-info/licenses/LICENSE
mcp_ai_jerry-2.0.13.dist-info/RECORD
