Metadata-Version: 2.4
Name: mcp-ai-jerry
Version: 2.0.13
Summary: MCP AI Jerry - 智能交互反馈 MCP 服务器，提供 Web UI 和桌面应用双重界面支持。
Author-email: Jerry <jerry@example.com>
License-File: LICENSE
Keywords: ai,desktop-app,development,feedback,interactive,mcp,web-ui
Classifier: Development Status :: 4 - Beta
Classifier: Intended Audience :: Developers
Classifier: Operating System :: OS Independent
Classifier: Programming Language :: Python :: 3
Classifier: Programming Language :: Python :: 3.11
Classifier: Programming Language :: Python :: 3.12
Classifier: Topic :: Software Development :: Libraries :: Python Modules
Requires-Python: >=3.11
Requires-Dist: aiohttp>=3.8.0
Requires-Dist: fastapi>=0.115.0
Requires-Dist: fastmcp>=2.0.0
Requires-Dist: httpx>=0.24.0
Requires-Dist: jinja2>=3.1.0
Requires-Dist: mcp>=1.9.3
Requires-Dist: psutil>=7.0.0
Requires-Dist: uvicorn>=0.30.0
Requires-Dist: websockets>=13.0.0
Provides-Extra: dev
Requires-Dist: pytest-asyncio>=0.21.0; extra == 'dev'
Requires-Dist: pytest>=7.0.0; extra == 'dev'
